Metadata-Version: 2.1
Name: hahahasillyxd
Version: 0.1
Summary: cantdoitanymorehaahahaaha
